chemFuncT/__init__.py
chemFuncT/chemFuncT.py
chemFuncT/sqlite_handler.py
chemFuncT/data/ChemFuncT.db
chemfunct-1.0.2.dist-info/licenses/LICENSE
chemfunct-1.0.2.dist-info/METADATA
chemfunct-1.0.2.dist-info/WHEEL
chemfunct-1.0.2.dist-info/top_level.txt
chemfunct-1.0.2.dist-info/RECORD
