Metadata-Version: 2.4
Name: ChemFuncT
Version: 1.0.2
Summary: Helper utilities for the Chemical Functional Use Taxonomy SQLite database.
Author: E. Tyler Carr
License: CC0-1.0
Project-URL: Homepage, https://github.com/carret1268/AMOS-ChemFuncT
Project-URL: Source, https://github.com/carret1268/AMOS-ChemFuncT
Classifier: Programming Language :: Python :: 3
Classifier: Programming Language :: Python :: 3.11
Classifier: Programming Language :: Python :: 3.12
Classifier: License :: CC0 1.0 Universal (CC0 1.0) Public Domain Dedication
Classifier: Intended Audience :: Science/Research
Classifier: Topic :: Scientific/Engineering
Requires-Python: >=3.11
License-File: LICENSE
Requires-Dist: openpyxl>=3.1
Dynamic: license-file
